sastools/__init__.py
sastools/_version.py
sastools/analyzer/__init__.py
sastools/analyzer/curvefitting.py
sastools/analyzer/enums.py
sastools/analyzer/llcphase.py
sastools/analyzer/llcphases.py
sastools/analyzer/sansanalyzers.py
sastools/analyzer/saxsanalyzers.py
sastools/readers/__init__.py
sastools/readers/infer_type.py
sastools/readers/originreader.py
sastools/readers/pdhreader.py
sastools/readers/seriesreader.py
sastools-0.3.3.dist-info/LICENSE
sastools-0.3.3.dist-info/METADATA
sastools-0.3.3.dist-info/WHEEL
sastools-0.3.3.dist-info/top_level.txt
sastools-0.3.3.dist-info/RECORD
