Metadata-Version: 2.1
Name: sastools
Version: 0.3.3
Summary: SAS-tools contains useful functions and classes for working with SAS data.
Author-email: Torsten Giess <torsten.giess@ibtb.uni-stuttgart.de>, Selina Itzigehl <selina.itzigehl@ipc.uni-stuttgart.de>, Jan Range <jan.range@simtech.uni-stuttgart.de>, Richard Schoemig <richard.schoemig@ibtb.uni-stuttgart.de>
Maintainer-email: FAIR Chemistry <fairchemistry@ibtb.uni-stuttgart.de>
License: MIT License        
Project-URL: Homepage, https://github.com/FAIRChemistry
Project-URL: Repository, https://github.com/FAIRChemistry/SAS-tools
Keywords: RDM,SAS,SAXS
Classifier: Development Status :: 4 - Beta
Classifier: Programming Language :: Python :: 3
Classifier: Topic :: Scientific/Engineering :: Chemistry
Requires-Python: >=3.10
License-File: LICENSE
Requires-Dist: lxml
Requires-Dist: numpy
Requires-Dist: pandas
Requires-Dist: pyaniml
